lifeomic_logging/__init__.py
lifeomic_logging/logger.py
lifeomic_logging/version.py
lifeomic_logging-0.4.0.dist-info/LICENSE
lifeomic_logging-0.4.0.dist-info/METADATA
lifeomic_logging-0.4.0.dist-info/WHEEL
lifeomic_logging-0.4.0.dist-info/top_level.txt
lifeomic_logging-0.4.0.dist-info/RECORD
