Metadata-Version: 2.1
Name: lifeomic_logging
Version: 0.4.0
Summary: LifeOmic Python Logging Library.
Home-page: https://github.com/lifeomic/logging-py
Author: LifeOmic Development
Author-email: development@lifeomic.com
License: MIT
Classifier: Development Status :: 3 - Alpha
Classifier: License :: OSI Approved :: MIT License
Classifier: Intended Audience :: Developers
Classifier: Intended Audience :: Healthcare Industry
Classifier: Natural Language :: English
Classifier: Programming Language :: Python
Classifier: Programming Language :: Python :: 3
Classifier: Programming Language :: Python :: 3.6
Classifier: Topic :: Utilities
License-File: LICENSE
